pinocchiout/__init__.py
pinocchiout/data.py
pinocchiout/main.py
pinocchiout/solver.py
pinocchiout/tableator.py
pinocchiout/utils.py
pinocchiout-0.3.0.dist-info/METADATA
pinocchiout-0.3.0.dist-info/WHEEL
pinocchiout-0.3.0.dist-info/entry_points.txt
pinocchiout-0.3.0.dist-info/licenses/LICENSE
pinocchiout-0.3.0.dist-info/RECORD
