Metadata-Version: 2.4
Name: pinocchiout
Version: 0.3.0
Summary: Pinout solver STM32 for microcontrollers
License-File: LICENSE
Requires-Python: >=3.13
Requires-Dist: groupie>=0.1.0
Requires-Dist: httpx>=0.28.1
Requires-Dist: pydantic>=2.11.7
Requires-Dist: rich>=14.0.0
Requires-Dist: ruamel-yaml>=0.18.14
Requires-Dist: typer>=0.16.0
Requires-Dist: z3-solver>=4.15.1.0
